{"version": "1", "message": "ERROR: Hidden Testcases server unreachable.", "problem_id": "ads2_m10_a1_1", "user_id": "saad181", "score": {"sample": {"0": {"execution_time": 0.5870726108551025, "passed": true}, "1": {"execution_time": 0.6046278476715088, "passed": true}, "2": {"execution_time": 0.4964282512664795, "passed": true}, "3": {"execution_time": 0.24548029899597168, "passed": true}, "4": {"execution_time": 1.168057918548584, "passed": true}, "5": {"execution_time": 1.1370043754577637, "passed": true}, "6": {"execution_time": 4.027737379074097, "passed": true}, "7": {"execution_time": 0.42829012870788574, "passed": true}, "8": {"execution_time": 3.2308597564697266, "passed": true}}}, "check_style_score": "0/1"}